simple_arn/__init__.py
simple_arn/simple_arn.py
simple_arn-0.0.3.dist-info/LICENSE.md
simple_arn-0.0.3.dist-info/METADATA
simple_arn-0.0.3.dist-info/WHEEL
simple_arn-0.0.3.dist-info/top_level.txt
simple_arn-0.0.3.dist-info/RECORD
