Metadata-Version: 2.1
Name: simple_arn
Version: 0.0.3
Summary: simple AWS arn parsing and serialization
Home-page: https://github.com/ericmaustin/aws_arn
Author: Eric Austin
Author-email: eric.m.austin@gmail.com
License: MIT
Requires-Python: >=3.7
License-File: LICENSE.md
